aioscrapy/VERSION
aioscrapy/__init__.py
aioscrapy/__main__.py
aioscrapy/cmdline.py
aioscrapy/crawler.py
aioscrapy/exceptions.py
aioscrapy/link.py
aioscrapy/logformatter.py
aioscrapy/process.py
aioscrapy/serializer.py
aioscrapy/signalmanager.py
aioscrapy/signals.py
aioscrapy/spiderloader.py
aioscrapy/statscollectors.py
aioscrapy/commands/__init__.py
aioscrapy/commands/crawl.py
aioscrapy/commands/genspider.py
aioscrapy/commands/list.py
aioscrapy/commands/runspider.py
aioscrapy/commands/settings.py
aioscrapy/commands/startproject.py
aioscrapy/commands/version.py
aioscrapy/core/__init__.py
aioscrapy/core/engine.py
aioscrapy/core/scheduler.py
aioscrapy/core/scraper.py
aioscrapy/core/downloader/__init__.py
aioscrapy/core/downloader/handlers/__init__.py
aioscrapy/core/downloader/handlers/aiohttp.py
aioscrapy/core/downloader/handlers/curl_cffi.py
aioscrapy/core/downloader/handlers/httpx.py
aioscrapy/core/downloader/handlers/pyhttpx.py
aioscrapy/core/downloader/handlers/requests.py
aioscrapy/core/downloader/handlers/webdriver/__init__.py
aioscrapy/core/downloader/handlers/webdriver/drissionpage.py
aioscrapy/core/downloader/handlers/webdriver/driverpool.py
aioscrapy/core/downloader/handlers/webdriver/playwright.py
aioscrapy/db/__init__.py
aioscrapy/db/absmanager.py
aioscrapy/db/aiomongo.py
aioscrapy/db/aiomysql.py
aioscrapy/db/aiopg.py
aioscrapy/db/aiorabbitmq.py
aioscrapy/db/aioredis.py
aioscrapy/dupefilters/__init__.py
aioscrapy/dupefilters/disk.py
aioscrapy/dupefilters/redis.py
aioscrapy/http/__init__.py
aioscrapy/http/headers.py
aioscrapy/http/request/__init__.py
aioscrapy/http/request/form.py
aioscrapy/http/request/json_request.py
aioscrapy/http/response/__init__.py
aioscrapy/http/response/html.py
aioscrapy/http/response/text.py
aioscrapy/http/response/web_driver.py
aioscrapy/http/response/xml.py
aioscrapy/libs/__init__.py
aioscrapy/libs/downloader/__init__.py
aioscrapy/libs/downloader/defaultheaders.py
aioscrapy/libs/downloader/downloadtimeout.py
aio_scrapy-2.1.8.dist-info/LICENSE
aio_scrapy-2.1.8.dist-info/METADATA
aio_scrapy-2.1.8.dist-info/WHEEL
aio_scrapy-2.1.8.dist-info/entry_points.txt
aio_scrapy-2.1.8.dist-info/top_level.txt
aio_scrapy-2.1.8.dist-info/RECORD
