Metadata-Version: 2.2
Name: aio-scrapy
Version: 2.1.8
Summary: A high-level Web Crawling and Web Scraping framework based on Asyncio
Home-page: https://github.com/conlin-huang/aio-scrapy.git
Author: conlin
Author-email: 995018884@qq.com
License: MIT
Keywords: aio-scrapy,scrapy,aioscrapy,scrapy redis,asyncio,spider
Classifier: License :: OSI Approved :: MIT License
Classifier: Intended Audience :: Developers
Classifier: Operating System :: OS Independent
Classifier: Programming Language :: Python :: 3.9
Classifier: Programming Language :: Python :: 3.10
Classifier: Programming Language :: Python :: 3.11
Classifier: Topic :: Internet :: WWW/HTTP
Classifier: Topic :: Software Development :: Libraries :: Application Frameworks
Classifier: Topic :: Software Development :: Libraries :: Python Modules
Requires-Python: >=3.9
License-File: LICENSE
Requires-Dist: aiohttp
Requires-Dist: ujson
Requires-Dist: w3lib>=1.17.0
Requires-Dist: parsel>=1.5.0
Requires-Dist: PyDispatcher>=2.0.5
Requires-Dist: zope.interface>=5.1.0
Requires-Dist: redis>=4.3.1
Requires-Dist: aiomultiprocess>=0.9.0
Requires-Dist: loguru>=0.7.0
Requires-Dist: anyio>=3.6.2
Provides-Extra: all
Requires-Dist: aiomysql>=0.1.1; extra == "all"
Requires-Dist: httpx[http2]>=0.23.0; extra == "all"
Requires-Dist: aio-pika>=8.1.1; extra == "all"
Requires-Dist: cryptography; extra == "all"
Requires-Dist: motor>=2.1.0; extra == "all"
Requires-Dist: pyhttpx>=2.10.1; extra == "all"
Requires-Dist: asyncpg>=0.27.0; extra == "all"
Requires-Dist: XlsxWriter>=3.1.2; extra == "all"
Requires-Dist: pillow>=9.4.0; extra == "all"
Requires-Dist: requests>=2.28.2; extra == "all"
Requires-Dist: curl_cffi; extra == "all"
Provides-Extra: aiomysql
Requires-Dist: aiomysql>=0.1.1; extra == "aiomysql"
Requires-Dist: cryptography; extra == "aiomysql"
Provides-Extra: httpx
Requires-Dist: httpx[http2]>=0.23.0; extra == "httpx"
Provides-Extra: aio-pika
Requires-Dist: aio-pika>=8.1.1; extra == "aio-pika"
Provides-Extra: mongo
Requires-Dist: motor>=2.1.0; extra == "mongo"
Provides-Extra: playwright
Requires-Dist: playwright>=1.31.1; extra == "playwright"
Provides-Extra: pyhttpx
Requires-Dist: pyhttpx>=2.10.4; extra == "pyhttpx"
Provides-Extra: curl-cffi
Requires-Dist: curl_cffi>=0.6.1; extra == "curl-cffi"
Provides-Extra: requests
Requires-Dist: requests>=2.28.2; extra == "requests"
Provides-Extra: pg
Requires-Dist: asyncpg>=0.27.0; extra == "pg"
Provides-Extra: execl
Requires-Dist: XlsxWriter>=3.1.2; extra == "execl"
Requires-Dist: pillow>=9.4.0; extra == "execl"
Dynamic: author
Dynamic: author-email
Dynamic: classifier
Dynamic: description
Dynamic: description-content-type
Dynamic: home-page
Dynamic: keywords
Dynamic: license
Dynamic: provides-extra
Dynamic: requires-dist
Dynamic: requires-python
Dynamic: summary
